.gitignore
LARBIN.md
MANIFEST.in
pytest.ini
setup.py
docs/Makefile
docs/conf.py
docs/index.rst
docs/make.bat
larbin/__init__.py
larbin/cli.py
larbin/context.py
larbin/db.py
larbin/diff.py
larbin/flow2.py
larbin/path.py
larbin/plugin.py
larbin/project.py
larbin/prompt2.py
larbin/tasks.py
larbin/template2.py
larbin.egg-info/PKG-INFO
larbin.egg-info/SOURCES.txt
larbin.egg-info/dependency_links.txt
larbin.egg-info/entry_points.txt
larbin.egg-info/requires.txt
larbin.egg-info/top_level.txt
larbin/flows/larbin.inspect.yml
larbin/plugins/__init__.py
larbin/plugins/ask.py
larbin/plugins/autocontext.py
larbin/plugins/code.py
larbin/plugins/do.py
larbin/plugins/inspect.py
larbin/plugins/plan.py
larbin/plugins/prompt.py
larbin/plugins/tdd.py
larbin/plugins/repomap/plugin.py
larbin/plugins/repomap/repo_map.py
larbin/plugins/repomap/scan_dir.py
larbin/plugins/repomap/scan_files.py
larbin/prompts/create_files_system.txt
larbin/prompts/fix_file.txt
larbin/prompts/fix_file_output.txt
larbin/prompts/fix_files_for_output.txt
larbin/prompts/irrelevant_directories_to_ignore.txt
larbin/prompts/larbin.context.build.txt
larbin/prompts/larbin.directions.txt
larbin/prompts/larbin.macros.txt
larbin/prompts/larbin.source.txt
larbin/prompts/macros.txt
larbin/templates/larbin.ask.txt
larbin/templates/larbin.autocontext.tests.txt
larbin/templates/larbin.autocontext.txt
larbin/templates/larbin.languages.txt
larbin/templates/larbin.macros.txt
larbin/templates/larbin.plan.txt