Metadata-Version: 2.4
Name: larbin
Version: 0.0.3
Home-page: https://github.com/yourlabs/larbin
Author: James Pic
Author-email: jamespic@gmail.com
License: MIT
Keywords: cli
Requires-Python: >=3.6
Requires-Dist: cli2
Requires-Dist: prompt2
Requires-Dist: flow2
Requires-Dist: tree-sitter
Requires-Dist: tree-sitter-language-pack
Requires-Dist: sqlalchemy[asyncio]
Requires-Dist: aiosqlite
Requires-Dist: networkx
Requires-Dist: markdown-it-py
Dynamic: author
Dynamic: author-email
Dynamic: home-page
Dynamic: keywords
Dynamic: license
Dynamic: requires-dist
Dynamic: requires-python
